numynal/__init__.py
numynal/db/__init__.py
numynal/db/connector.py
numynal/db/csv_connector.py
numynal/eda/__init__.py
numynal/ml/__init__.py
numynal/preprocessing/__init__.py
numynal/stats/__init__.py
numynal/utils/__init__.py
numynal/visualization/__init__.py
numynal-0.1.1.dist-info/METADATA
numynal-0.1.1.dist-info/WHEEL
numynal-0.1.1.dist-info/top_level.txt
numynal-0.1.1.dist-info/RECORD
