Metadata-Version: 2.1
Name: numynal
Version: 0.1.1
Summary: A comprehensive data anlysis library
Home-page: https://github.com/affanhamid/numynal
Author: Affan Hamid
Author-email: affanhamid007@gmail.com
Classifier: Programming Language :: Python :: 3
Classifier: License :: OSI Approved :: MIT License
Classifier: Operating System :: OS Independent
Requires-Python: >=3.10
Requires-Dist: pandas
